{
    "schema":  "leaf.logbook.flight",
    "schema_version":  "v0.1.0",
    "flight_id":  "88e929de",
    "clock":  {
                  "system_time_synced_this_boot":  true,
                  "time_source":  "gps",
                  "timezone_offset_minutes":  -420
              },
    "start":  {
                  "time_utc":  "2025-06-14T21:09:00Z",
                  "time_local":  "2025-06-14T14:09:00",
                  "time_valid":  true,
                  "location":  {
                                   "lat_deg":  37.8404,
                                   "lon_deg":  -122.0574,
                                   "altitude_m":  786
                               },
                  "temperature_c":  15.6
              },
    "first_fix":  {
                      "time_utc":  "2025-06-14T21:09:12Z",
                      "time_local":  "2025-06-14T14:09:12",
                      "time_valid":  true,
                      "location":  {
                                       "lat_deg":  37.8406,
                                       "lon_deg":  -122.0576,
                                       "altitude_m":  790
                                   },
                      "temperature_c":  15.6
                  },
    "end":  {
                "time_utc":  "2025-06-14T21:52:54Z",
                "time_local":  "2025-06-14T14:52:54",
                "time_valid":  true,
                "location":  {
                                 "lat_deg":  37.8394,
                                 "lon_deg":  -122.0524,
                                 "altitude_m":  732
                             },
                "temperature_c":  16
            },
    "metrics":  {
                    "duration_seconds":  2634,
                    "max_altitude_m":  1878,
                    "min_altitude_m":  666,
                    "max_altitude_above_launch_m":  1092,
                    "max_climb_rate_mps":  1.8,
                    "max_sink_rate_mps":  -2.3,
                    "max_ground_speed_mps":  19.4,
                    "average_ground_speed_mps":  13.55,
                    "straight_line_distance_m":  14279,
                    "path_distance_m":  35698,
                    "max_accel_g":  1.13,
                    "min_accel_g":  0.82,
                    "max_temperature_c":  29.8,
                    "min_temperature_c":  14.6
                },
    "track":  {
                  "saved":  false
              },
    "device":  {
                   "firmware_version":  "0.1.7-test+h3.2.6",
                   "hardware_version":  "leaf_3_2_6",
                   "mac_address":  "AA:BB:CC:DD:EE:FF"
               },
    "pilot":  {
                  "id":  "pilot_3",
                  "name":  "Casey Lee"
              },
    "glider":  {
                   "id":  "glider_3",
                   "brand":  "Niviuk",
                   "model":  "Klimber",
                   "size":  "P",
                   "display_name":  "Klimber P"
               },
    "site":  {
                 "launch_name":  "Eagle Launch",
                 "landing_name":  "Main LZ"
             },
    "weather":  {

                },
    "notes":  {
                  "pilot_notes":  "",
                  "tags":  [

                           ]
              }
}
