{
    "schema":  "leaf.logbook.flight",
    "schema_version":  "v0.1.0",
    "flight_id":  "ad77305b",
    "clock":  {
                  "system_time_synced_this_boot":  true,
                  "time_source":  "gps",
                  "timezone_offset_minutes":  -420
              },
    "start":  {
                  "time_utc":  "2025-07-31T21:09:00Z",
                  "time_local":  "2025-07-31T14:09:00",
                  "time_valid":  true,
                  "location":  {
                                   "lat_deg":  37.3607,
                                   "lon_deg":  -122.1537,
                                   "altitude_m":  2203
                               },
                  "temperature_c":  23.3
              },
    "first_fix":  {
                      "time_utc":  "2025-07-31T21:09:12Z",
                      "time_local":  "2025-07-31T14:09:12",
                      "time_valid":  true,
                      "location":  {
                                       "lat_deg":  37.3609,
                                       "lon_deg":  -122.1539,
                                       "altitude_m":  2207
                                   },
                      "temperature_c":  23.3
                  },
    "end":  {
                "time_utc":  "2025-07-31T21:19:27Z",
                "time_local":  "2025-07-31T14:19:27",
                "time_valid":  true,
                "location":  {
                                 "lat_deg":  37.3627,
                                 "lon_deg":  -122.1577,
                                 "altitude_m":  1946
                             },
                "temperature_c":  14.5
            },
    "metrics":  {
                    "duration_seconds":  627,
                    "max_altitude_m":  2434,
                    "min_altitude_m":  1883,
                    "max_altitude_above_launch_m":  231,
                    "max_climb_rate_mps":  2.7,
                    "max_sink_rate_mps":  -4.7,
                    "max_ground_speed_mps":  13.7,
                    "average_ground_speed_mps":  23.2,
                    "straight_line_distance_m":  4801,
                    "path_distance_m":  14549,
                    "max_accel_g":  1.18,
                    "min_accel_g":  0.87,
                    "max_temperature_c":  16.9,
                    "min_temperature_c":  14.3
                },
    "track":  {
                  "saved":  false
              },
    "device":  {
                   "firmware_version":  "0.1.7-test+h3.2.6",
                   "hardware_version":  "leaf_3_2_6",
                   "mac_address":  "AA:BB:CC:DD:EE:FF"
               },
    "pilot":  {
                  "id":  "pilot_4",
                  "name":  "Taylor Quinn"
              },
    "glider":  {
                   "id":  "glider_4",
                   "brand":  "Gin",
                   "model":  "Bonanza",
                   "size":  "S",
                   "display_name":  "Bonanza S"
               },
    "site":  {
                 "launch_name":  "West Spur",
                 "landing_name":  "Main LZ"
             },
    "weather":  {

                },
    "notes":  {
                  "pilot_notes":  "",
                  "tags":  [

                           ]
              }
}
